LICENSE
NOTICE
algoseek_connector/__init__.py
algoseek_connector/base.py
algoseek_connector/clickhouse/__init__.py
algoseek_connector/clickhouse/alias.json
algoseek_connector/clickhouse/case_insensitive.json
algoseek_connector/clickhouse/client.py
algoseek_connector/clickhouse/sqla_table.py
algoseek_connector/dataset_api.py
algoseek_connector/default-config.toml
algoseek_connector/manager.py
algoseek_connector/models.py
algoseek_connector/s3/__init__.py
algoseek_connector/s3/client.py
algoseek_connector/s3/downloader.py
algoseek_connector/settings.py
algoseek_connector/utils.py
algoseek_connector-2.1.5.dist-info/LICENSE
algoseek_connector-2.1.5.dist-info/METADATA
algoseek_connector-2.1.5.dist-info/NOTICE
algoseek_connector-2.1.5.dist-info/WHEEL
algoseek_connector-2.1.5.dist-info/RECORD
