Metadata-Version: 2.1
Name: algoseek-connector
Version: 2.1.5
Summary: A library for fetching Algoseek datasets using SQL-like queries
License: Apache-2.0
Author: algoseek
Author-email: support@algoseek.com
Requires-Python: >=3.10,<4.0
Classifier: Development Status :: 4 - Beta
Classifier: Environment :: Console
Classifier: Intended Audience :: Developers
Classifier: Intended Audience :: Information Technology
Classifier: License :: OSI Approved :: Apache Software License
Classifier: Operating System :: OS Independent
Classifier: Programming Language :: Python :: 3
Classifier: Programming Language :: Python :: 3.10
Classifier: Programming Language :: Python :: 3.11
Classifier: Programming Language :: Python :: 3.12
Classifier: Programming Language :: Python :: 3.13
Classifier: Programming Language :: SQL
Classifier: Topic :: Database
Classifier: Topic :: Software Development
Classifier: Topic :: Software Development :: Libraries
Classifier: Topic :: Software Development :: Libraries :: Python Modules
Requires-Dist: boto3 (>=1.28.11,<2.0.0)
Requires-Dist: botocore (>=1.31.12,<2.0.0)
Requires-Dist: clickhouse-connect (>=0.6.6,<0.7.0)
Requires-Dist: clickhouse-sqlalchemy (>=0.2.4,<0.3.0)
Requires-Dist: pandas (>=2.0.2,<3.0.0)
Requires-Dist: pendulum (>=3.0.0,<4.0.0)
Requires-Dist: pydantic (>=2.7.1,<3.0.0)
Requires-Dist: pydantic-settings (>=2.2.1,<3.0.0)
Requires-Dist: requests (>=2.31.0,<3.0.0)
Requires-Dist: sqlalchemy (>=1.4,<2.0)
Requires-Dist: sqlparse (>=0.5.0,<0.6.0)
Requires-Dist: tomli (>=2.0.1,<3.0.0)
Project-URL: Documentation, https://algoseek-connector.readthedocs.io/
Project-URL: GitHub, https://github.com/algoseekgit/algoseek-connector/
